itllib/__init__.py
itllib/__main__.py
itllib/clusters.py
itllib/itl.py
itllib/loops.py
itllib/piles.py
itllib/resources.py
itllib/secrets.py
itllib/controllers/__init__.py
itllib/controllers/propagation_operator.py
itllib/controllers/resource_controller.py
itllib/controllers/resource_monitor.py
itllib-0.0.11.dist-info/METADATA
itllib-0.0.11.dist-info/WHEEL
itllib-0.0.11.dist-info/licenses/LICENSE
itllib-0.0.11.dist-info/RECORD
