Metadata-Version: 2.3
Name: itllib
Version: 0.0.11
Summary: Utility functions for provisioning
Author-email: That Dev <sunny@thatone.ai>
License-File: LICENSE
Classifier: Operating System :: POSIX :: Linux
Classifier: Programming Language :: Python :: 3
Requires-Python: >=3.7
Requires-Dist: aiohttp
Requires-Dist: boto3
Requires-Dist: fire
Requires-Dist: httpx
Requires-Dist: pydantic
Requires-Dist: pyyaml
Requires-Dist: requests
Requires-Dist: websockets
